cdwave/__init__.py
cdwave/data.py
cdwave/derive.py
cdwave/fnc.py
cdwave/hillcurve.py
cdwave/model.py
cdwave/param.py
cdwave/param_annot.json
cdwave/parameters.csv
tests/__init__.py
tests/test_data.py
tests/test_fnc.py
tests/test_hill.py
tests/test_param.py
CardioWave-0.2.3.dist-info/LICENSE
CardioWave-0.2.3.dist-info/METADATA
CardioWave-0.2.3.dist-info/WHEEL
CardioWave-0.2.3.dist-info/top_level.txt
CardioWave-0.2.3.dist-info/RECORD
