Metadata-Version: 2.1
Name: CardioWave
Version: 0.2.3
Summary: A tool to derive parameters from waveform data for cardiotoxicity research
Home-page: https://github.com/zealseeker/cardiowave
Author: Hongbin Yang
Author-email: yanyanghong@163.com
License: UNKNOWN
Platform: UNKNOWN
Classifier: Programming Language :: Python :: 3
Classifier: License :: OSI Approved :: MIT License
Classifier: Operating System :: OS Independent
License-File: LICENSE
Requires-Dist: statsmodels
Requires-Dist: tqdm
Requires-Dist: joblib
